README.md
setup.py
src/crucyble/__init__.py
src/crucyble/decorators.py
src/crucyble/glove.py
src/crucyble/logging.py
src/crucyble/stages.py
src/crucyble/types.py
src/crucyble/verbosity.py
src/crucyble.egg-info/PKG-INFO
src/crucyble.egg-info/SOURCES.txt
src/crucyble.egg-info/dependency_links.txt
src/crucyble.egg-info/top_level.txt
src/crucyble/lib/__init__.py
src/lib/cooccur.c
src/lib/glove.c
src/lib/shuffle.c
src/lib/vocab_count.c
src/lib/glove/cooccur.c
src/lib/glove/glove.c
src/lib/glove/shuffle.c
src/lib/glove/vocab_count.c
test/test_glove.py