Metadata-Version: 2.1
Name: crucyble
Version: 0.1.0.dev3
Summary: A Cython Wrapped GloVe
Home-page: https://github.com/ttymck/crucyble
Author: Tyler Kontra
Author-email: tyler@tylerkontra.com
License: UNKNOWN
Platform: UNKNOWN
Requires-Python: >=3.7,<4.0
